dlms_cosem/__init__.py
dlms_cosem/a_xdr.py
dlms_cosem/ber.py
dlms_cosem/client.py
dlms_cosem/connection.py
dlms_cosem/crc.py
dlms_cosem/dlms_data.py
dlms_cosem/enumerations.py
dlms_cosem/exceptions.py
dlms_cosem/io.py
dlms_cosem/parsers.py
dlms_cosem/security.py
dlms_cosem/state.py
dlms_cosem/time.py
dlms_cosem/utils.py
dlms_cosem/cosem/__init__.py
dlms_cosem/cosem/association.py
dlms_cosem/cosem/attribute_with_selection.py
dlms_cosem/cosem/base.py
dlms_cosem/cosem/capture_object.py
dlms_cosem/cosem/obis.py
dlms_cosem/cosem/profile_generic.py
dlms_cosem/cosem/selective_access.py
dlms_cosem/hdlc/__init__.py
dlms_cosem/hdlc/address.py
dlms_cosem/hdlc/connection.py
dlms_cosem/hdlc/exceptions.py
dlms_cosem/hdlc/fields.py
dlms_cosem/hdlc/frames.py
dlms_cosem/hdlc/state.py
dlms_cosem/hdlc/validators.py
dlms_cosem/protocol/__init__.py
dlms_cosem/protocol/wrappers.py
dlms_cosem/protocol/acse/__init__.py
dlms_cosem/protocol/acse/aare.py
dlms_cosem/protocol/acse/aarq.py
dlms_cosem/protocol/acse/base.py
dlms_cosem/protocol/acse/rlre.py
dlms_cosem/protocol/acse/rlrq.py
dlms_cosem/protocol/acse/user_information.py
dlms_cosem/protocol/xdlms/__init__.py
dlms_cosem/protocol/xdlms/action.py
dlms_cosem/protocol/xdlms/base.py
dlms_cosem/protocol/xdlms/confirmed_service_error.py
dlms_cosem/protocol/xdlms/conformance.py
dlms_cosem/protocol/xdlms/data_notification.py
dlms_cosem/protocol/xdlms/exception_response.py
dlms_cosem/protocol/xdlms/general_global_cipher.py
dlms_cosem/protocol/xdlms/get.py
dlms_cosem/protocol/xdlms/initiate_request.py
dlms_cosem/protocol/xdlms/initiate_response.py
dlms_cosem/protocol/xdlms/invoke_id_and_priority.py
dlms_cosem/protocol/xdlms/set.py
tests/test_asce/__init__.py
tests/test_asce/test_aare.py
tests/test_asce/test_aarq.py
tests/test_asce/test_conformance.py
tests/test_asce/test_rlre.py
tests/test_asce/test_rlrq.py
tests/test_clients/__init__.py
tests/test_clients/test_dlms_client.py
tests/test_hdlc/__init__.py
tests/test_hdlc/test_hdlc.py
dlms_cosem-25.1.0.dist-info/LICENSE
dlms_cosem-25.1.0.dist-info/METADATA
dlms_cosem-25.1.0.dist-info/WHEEL
dlms_cosem-25.1.0.dist-info/top_level.txt
dlms_cosem-25.1.0.dist-info/RECORD
