Metadata-Version: 2.1
Name: dlms-cosem
Version: 25.1.0
Summary: A Python library for DLMS/COSEM
Home-page: https://github.com/pwitab/dlms-cosem
Author: Henrik Palmlund Wahlgren @ Palmlund Wahlgren Innovative Technology AB
Author-email: henrik@pwit.se
Maintainer: Henrik Palmlund Wahlgren @ Palmlund Wahlgren Innovative Technology AB
Maintainer-email: henrik@pwit.se
License: MIT
Project-URL: Documentation, https://www.dlms.dev/
Project-URL: Bug Tracker, https://github.com/pwitab/dlms-cosem/issues
Project-URL: Source Code, https://github.com/pwitab/dlms-cosem
Keywords: AMR,Metering,smart meters,MDM,dlms,cosem
Classifier: Intended Audience :: Developers
Classifier: Natural Language :: English
Classifier: License :: Other/Proprietary License
Classifier: Operating System :: OS Independent
Classifier: Programming Language :: Python :: 3
Classifier: Programming Language :: Python :: 3 :: Only
Classifier: Programming Language :: Python :: 3.7
Classifier: Programming Language :: Python :: 3.8
Classifier: Programming Language :: Python :: 3.9
Classifier: Programming Language :: Python :: 3.10
Classifier: Programming Language :: Python :: Implementation :: CPython
Classifier: Topic :: Software Development :: Libraries :: Python Modules
Classifier: Topic :: Communications
Requires-Python: ~=3.7
License-File: LICENSE
Requires-Dist: attrs >=22.2.0
Requires-Dist: pyserial >=3.5
Requires-Dist: cryptography >=35.0.0
Requires-Dist: asn1crypto >=1.4.0
Requires-Dist: python-dateutil >=2.8.1
Requires-Dist: typing-extensions >=3.10
Requires-Dist: structlog >=22.1.0
Provides-Extra: dev
Requires-Dist: pre-commit ; extra == 'dev'
Requires-Dist: mkdocs ; extra == 'dev'
Requires-Dist: mkdocs-material ; extra == 'dev'
Requires-Dist: pytest ; extra == 'dev'
Requires-Dist: pytest-cov ; extra == 'dev'
Requires-Dist: pytest-sugar ; extra == 'dev'
Provides-Extra: docs
Requires-Dist: mkdocs ; extra == 'docs'
Requires-Dist: mkdocs-material ; extra == 'docs'
Provides-Extra: test
Requires-Dist: pytest ; extra == 'test'
Requires-Dist: pytest-cov ; extra == 'test'
Requires-Dist: pytest-sugar ; extra == 'test'
